sparkplug/__init__.py
sparkplug/cli.py
sparkplug/digraph.py
sparkplug/examples.py
sparkplug/executor.py
sparkplug/logutils.py
sparkplug/options.py
sparkplug/config/__init__.py
sparkplug/config/binding.py
sparkplug/config/connection.py
sparkplug/config/consumer.py
sparkplug/config/exchange.py
sparkplug/config/heartbeater.py
sparkplug/config/queue.py
sparkplug/config/timer.py
sparkplug/config/timereporter.py
sparkplug/config/types.py
sparkplug/timereporters/__init__.py
sparkplug/timereporters/base.py
sparkplug/timereporters/logger.py
sparkplug/timereporters/statsd.py
sparkplug-1.22.0.dist-info/LICENSE
sparkplug-1.22.0.dist-info/METADATA
sparkplug-1.22.0.dist-info/WHEEL
sparkplug-1.22.0.dist-info/entry_points.txt
sparkplug-1.22.0.dist-info/top_level.txt
sparkplug-1.22.0.dist-info/RECORD
