Metadata-Version: 2.1
Name: sparkplug
Version: 1.22.0
Summary: An AMQP message consumer daemon
Home-page: https://github.com/freshbooks/sparkplug/
Maintainer: FreshBooks
Maintainer-email: dev@freshbooks.com
License: UNKNOWN
Download-URL: https://pypi.python.org/pypi/sparkplug/
Platform: UNKNOWN
Classifier: Development Status :: 5 - Production/Stable
Classifier: Environment :: Console
Classifier: Environment :: No Input/Output (Daemon)
Classifier: Intended Audience :: Developers
Classifier: License :: OSI Approved :: MIT License
Classifier: Operating System :: POSIX
Classifier: Topic :: Software Development :: Libraries :: Application Frameworks
Classifier: Topic :: Software Development :: Libraries :: Python Modules
Classifier: Topic :: System :: Distributed Computing
Classifier: Topic :: Utilities
Requires-Dist: amqp (>=2.3.2)
Requires-Dist: lockfile (<0.13,>=0.9.1)
Requires-Dist: configparser (<6.0,>=3.5)
